sharded/__init__.py
sharded/cli.py
sharded_py-0.0.2.dist-info/LICENSE
sharded_py-0.0.2.dist-info/METADATA
sharded_py-0.0.2.dist-info/WHEEL
sharded_py-0.0.2.dist-info/RECORD
